mlqtl/__init__.py
mlqtl/__main__.py
mlqtl/cli.py
mlqtl/datautils.py
mlqtl/nda_typing.py
mlqtl/plot.py
mlqtl/py.typed
mlqtl/train.py
mlqtl/utils.py
mlqtl/data/__init__.py
mlqtl/data/dataset.py
mlqtl/data/gene.py
mlqtl/data/plink.py
mlqtl/data/snp.py
mlqtl/data/trait.py
mlqtl-0.1.8.dist-info/licenses/LICENSE
mlqtl-0.1.8.dist-info/METADATA
mlqtl-0.1.8.dist-info/WHEEL
mlqtl-0.1.8.dist-info/entry_points.txt
mlqtl-0.1.8.dist-info/top_level.txt
mlqtl-0.1.8.dist-info/RECORD
