Metadata-Version: 2.4
Name: mlqtl
Version: 0.1.8
Summary: A Python package for QTL detection based on machine learning
Requires-Python: >=3.12
License-File: LICENSE
Requires-Dist: click>=8.2.1
Requires-Dist: numpy<2.3.0
Requires-Dist: contourpy<=1.3.2
Requires-Dist: matplotlib<=3.9.4
Requires-Dist: pandas<=2.3.2
Requires-Dist: scikit-learn<=1.7.1
Requires-Dist: scipy<=1.15.3
Dynamic: license-file
